codeorigins/__init__.py
codeorigins/cli.py
codeorigins/common.py
codeorigins/composer.py
codeorigins/settings.py
codeorigins/utils.py
codeorigins/fetchers/__init__.py
codeorigins/fetchers/api.py
codeorigins/fetchers/base.py
codeorigins/templates/_base.html
codeorigins/templates/index.html
codeorigins/templates/page.html
codeorigins/templates/sub_countries.html
codeorigins/templates/sub_meta.html
codeorigins/templates/sub_metrika_counter.html
codeorigins/templates/sub_metrika_informer.html
codeorigins-0.3.1.dist-info/AUTHORS
codeorigins-0.3.1.dist-info/LICENSE
codeorigins-0.3.1.dist-info/METADATA
codeorigins-0.3.1.dist-info/WHEEL
codeorigins-0.3.1.dist-info/entry_points.txt
codeorigins-0.3.1.dist-info/top_level.txt
codeorigins-0.3.1.dist-info/RECORD
