Metadata-Version: 2.1
Name: codeorigins
Version: 0.3.1
Summary: Code origins contest based on GitHub data
Home-page: https://github.com/idlesign/codeorigins
Author: Igor `idle sign` Starikov
Author-email: idlesign@yandex.ru
License: BSD 3-Clause License
Platform: UNKNOWN
Classifier: Development Status :: 4 - Beta
Classifier: Operating System :: OS Independent
Classifier: Programming Language :: Python
Classifier: Programming Language :: Python :: 3
Classifier: Programming Language :: Python :: 3.6
Classifier: Programming Language :: Python :: 3.7
Classifier: Programming Language :: Python :: 3.8
Classifier: License :: OSI Approved :: BSD License
Requires-Dist: Jinja2
Requires-Dist: click
Requires-Dist: requests
